iCE40-UP5K/full_adder/full_adder.v
module full_adder(
    input       a,
    input       b,
    input       c,

    output      s,
    output      c_out
);

wire a_xor_b;
assign a_xor_b = a ^ b;
assign s = a_xor_b ^ c;

wire a_xor_b_and_c;
assign a_xor_b_and_c = a_xor_b & c;
wire a_and_b;
assign a_and_b = a & b;
assign c_out = a_and_b | a_xor_b_and_c;

endmodule

iCE40-UP5K/full_adder/full_adder_tb.v
// define timescale for simulation
`timescale 1 ns / 10 ps
`include "assert.v"

module full_adder_tb();

    reg a = 0;
    reg b = 0;
    reg c = 0;

    wire s;
    wire c_out;
    
    localparam DURATION = 200;

    full_adder uut (
        .a(a),
        .b(b),
        .c(c),
        .s(s),
        .c_out(c_out)
    );

    initial begin
        // 0 0 0
        a = 0;
        b = 0;
        c = 0;
        #10
        `assert(s, 0);
        `assert(c_out, 0);
        #10

        // 0 0 1
        a = 0;
        b = 0;
        c = 1;
        #10
        `assert(s, 1);
        `assert(c_out, 0);
        #10

        // 0 1 0
        a = 0;
        b = 1;
        c = 0;
        #10
        `assert(s, 1);
        `assert(c_out, 0);
        #10
        
        // 1 0 0
        a = 1;
        b = 0;
        c = 0;
        #10
        `assert(s, 1);
        `assert(c_out, 0);
        #10

        // 0 1 1
        a = 0;
        b = 1;
        c = 1;
        #10
        `assert(s, 0);
        `assert(c_out, 1);
        #10

        // 1 0 1
        a = 1;
        b = 0;
        c = 1;
        #10
        `assert(s, 0);
        `assert(c_out, 1);
        #10

        // 1 1 0
        a = 1;
        b = 1;
        c = 0;
        #10
        `assert(s, 0);
        `assert(c_out, 1);
        #10

        // 1 1 1
        a = 1;
        b = 1;
        c = 1;
        #10
        `assert(s, 1);
        `assert(c_out, 1);

    end

    initial begin
        $dumpfile("full_adder_tb.vcd");
        $dumpvars(0, full_adder_tb);
        #(DURATION)
        $display("Finished.");
        $finish;
    end

endmodule

iCE40-UP5K/full_adder/full_adder_tb.vcd
$date
	Wed Oct 18 13:55:48 2023
$end
$version
	Icarus Verilog
$end
$timescale
	1ps
$end
$scope module full_adder_tb $end
$var wire 1 ! s $end
$var wire 1 " c_out $end
$var reg 1 # a $end
$var reg 1 $ b $end
$var reg 1 % c $end
$scope module uut $end
$var wire 1 # a $end
$var wire 1 & a_and_b $end
$var wire 1 ' a_xor_b $end
$var wire 1 ( a_xor_b_and_c $end
$var wire 1 $ b $end
$var wire 1 % c $end
$var wire 1 " c_out $end
$var wire 1 ! s $end
$upscope $end
$upscope $end
$enddefinitions $end
#0
$dumpvars
0(
0'
0&
0%
0$
0#
0"
0!
$end
#20000
1!
1%
#40000
1'
0%
1$
#60000
0$
1#
#80000
1"
0!
1(
1%
1$
0#
#100000
0$
1#
#120000
0(
0'
1&
0%
1$
#140000
1!
1%
